django_easyboard-0.1.0.dist-info/licenses/LICENSE
easyboard/__init__.py
easyboard/admin.py
easyboard/apps.py
easyboard/settings.py
easyboard/urls.py
easyboard/views.py
easyboard/crud/__init__.py
easyboard/crud/urls.py
easyboard/crud/views.py
easyboard/dashboard/__init__.py
easyboard/integration/__init__.py
easyboard/integration/constance.py
easyboard/integration/drf.py
easyboard/integration/dynamic_preferences.py
easyboard/integration/import_export/__init__.py
easyboard/integration/import_export/urls.py
easyboard/integration/import_export/views.py
easyboard/integration/mptt/__init__.py
easyboard/integration/mptt/urls.py
easyboard/integration/mptt/views.py
easyboard/static/.gitkeep
easyboard/templates/.gitkeep
easyboard/templates/easyboard/api_docs.html
easyboard/templates/easyboard/dashboard.html
easyboard/templates/easyboard/settings.html
django_easyboard-0.1.0.dist-info/METADATA
django_easyboard-0.1.0.dist-info/WHEEL
django_easyboard-0.1.0.dist-info/top_level.txt
django_easyboard-0.1.0.dist-info/RECORD
